{
  "updated": "04-07-2026 09:54",
  "stations": [
    {
      "name": "Desenzano",
      "wind": 4.3,
      "dir": "SSW",
      "max": 12.7,
      "maxTime": "09:54",
      "last": "04-07-2026 09:54"
    },
    {
      "name": "Peschiera",
      "wind": 2.2,
      "dir": "E",
      "max": 7.9,
      "maxTime": "09:54",
      "last": "04-07-2026 09:54"
    },
    {
      "name": "Salò",
      "wind": 4.4,
      "dir": "NNW",
      "max": 10.9,
      "maxTime": "09:54",
      "last": "04-07-2026 09:54"
    },
    {
      "name": "Toscolano",
      "wind": 17.4,
      "dir": "NE",
      "max": 20.0,
      "maxTime": "09:54",
      "last": "04-07-2026 09:54"
    },
    {
      "name": "Gargnano",
      "wind": 18.2,
      "dir": "SSW",
      "max": 21.5,
      "maxTime": "09:54",
      "last": "04-07-2026 09:54"
    },
    {
      "name": "Campione del Garda",
      "wind": 18.8,
      "dir": "W",
      "max": 25.2,
      "maxTime": "09:54",
      "last": "04-07-2026 09:54"
    },
    {
      "name": "Malcesine",
      "wind": 8.7,
      "dir": "E",
      "max": 11.6,
      "maxTime": "09:54",
      "last": "04-07-2026 09:54"
    }
  ]
}